{"businesses": [{"id": "xg2v81v53-H4DPyXWodYXQ", "alias": "bergen-audio-visual-bergenfield", "name": "Bergen Audio Visual", "image_url": "https://s3-media3.fl.yelpcdn.com/bphoto/OGUFtvMxKm5-dMhrl48lnQ/o.jpg", "is_closed": false, "url": "https://www.yelp.com/biz/bergen-audio-visual-bergenfield?adjust_creative=OD45_sigUUSBobJ_eVs01w&utm_campaign=yelp_api_v3&utm_medium=api_v3_business_search&utm_source=OD45_sigUUSBobJ_eVs01w", "review_count": 5, "categories": [{"alias": "partyequipmentrentals", "title": "Party Equipment Rentals"}, {"alias": "festivals", "title": "Festivals"}, {"alias": "eventplanning", "title": "Party & Event Planning"}], "rating": 5.0, "coordinates": {"latitude": 40.92703, "longitude": -73.99898}, "transactions": [], "location": {"address1": "24 S Front St", "address2": null, "address3": null, "city": "Bergenfield", "zip_code": "07621", "country": "US", "state": "NJ", "display_address": ["24 S Front St", "Bergenfield, NJ 07621"]}, "phone": "+12018202016", "display_phone": "(201) 820-2016", "distance": 24527.566404659767}, {"id": "H3gBNzvKUur0r6kiQth-BA", "alias": "new-york-citys-village-halloween-parade-new-york", "name": "New York City's Village Halloween Parade", "image_url": "https://s3-media1.fl.yelpcdn.com/bphoto/pXbLHaq5TK31nK6wJFFKhA/o.jpg", "is_closed": false, "url": "https://www.yelp.com/biz/new-york-citys-village-halloween-parade-new-york?adjust_creative=OD45_sigUUSBobJ_eVs01w&utm_campaign=yelp_api_v3&utm_medium=api_v3_business_search&utm_source=OD45_sigUUSBobJ_eVs01w", "review_count": 20, "categories": [{"alias": "festivals", "title": "Festivals"}], "rating": 4.5, "coordinates": {"latitude": 40.7254954, "longitude": -74.0040538}, "transactions": [], "location": {"address1": "6TH Ave And Spring St", "address2": "", "address3": "", "city": "New York", "zip_code": "10013", "country": "US", "state": "NY", "display_address": ["6TH Ave And Spring St", "New York, NY 10013"]}, "phone": "", "display_phone": "", "distance": 2938.0336215759185}, {"id": "sysY_MknQ7G97bUjSic_oA", "alias": "jump-into-vr-fest-new-york", "name": "Jump Into VR Fest", "image_url": "https://s3-media1.fl.yelpcdn.com/bphoto/0BeBTJnMkSI7mK0qEeropw/o.jpg", "is_closed": false, "url": "https://www.yelp.com/biz/jump-into-vr-fest-new-york?adjust_creative=OD45_sigUUSBobJ_eVs01w&utm_campaign=yelp_api_v3&utm_medium=api_v3_business_search&utm_source=OD45_sigUUSBobJ_eVs01w", "review_count": 1, "categories": [{"alias": "festivals", "title": "Festivals"}], "rating": 5.0, "coordinates": {"latitude": 40.72178, "longitude": -73.98824}, "transactions": [], "location": {"address1": "180 Orchard St", "address2": "", "address3": null, "city": "New York", "zip_code": "10002", "country": "US", "state": "NY", "display_address": ["180 Orchard St", "New York, NY 10002"]}, "phone": "+13472831925", "display_phone": "(347) 283-1925", "distance": 1826.538903860309}, {"id": "73aOGFOl2b8fdFEWk5CExQ", "alias": "pirate-school-and-other-madcap-characters-of-david-engel-hastings-on-hudson-2", "name": "Pirate School! and other madcap characters of David Engel", "image_url": "https://s3-media2.fl.yelpcdn.com/bphoto/vMmrlGZq_-jLIaIy3jkOlA/o.jpg", "is_closed": false, "url": "https://www.yelp.com/biz/pirate-school-and-other-madcap-characters-of-david-engel-hastings-on-hudson-2?adjust_creative=OD45_sigUUSBobJ_eVs01w&utm_campaign=yelp_api_v3&utm_medium=api_v3_business_search&utm_source=OD45_sigUUSBobJ_eVs01w", "review_count": 1, "categories": [{"alias": "theater", "title": "Performing Arts"}, {"alias": "festivals", "title": "Festivals"}], "rating": 5.0, "coordinates": {"latitude": 40.98472041827005, "longitude": -73.8839272}, "transactions": [], "location": {"address1": "24 Pinecrest Dr", "address2": "", "address3": "", "city": "Hastings-on-Hudson", "zip_code": "10706", "country": "US", "state": "NY", "display_address": ["24 Pinecrest Dr", "Hastings-on-Hudson, NY 10706"]}, "phone": "+13472627350", "display_phone": "(347) 262-7350", "distance": 31906.092750395328}, {"id": "geKUbMeeUAt-U9OSxqWCIA", "alias": "brooklyn-comedy-festival-brooklyn", "name": "Brooklyn Comedy Festival", "image_url": "https://s3-media3.fl.yelpcdn.com/bphoto/qaCbPLpuQql76_hyvlMWRA/o.jpg", "is_closed": false, "url": "https://www.yelp.com/biz/brooklyn-comedy-festival-brooklyn?adjust_creative=OD45_sigUUSBobJ_eVs01w&utm_campaign=yelp_api_v3&utm_medium=api_v3_business_search&utm_source=OD45_sigUUSBobJ_eVs01w", "review_count": 1, "categories": [{"alias": "festivals", "title": "Festivals"}], "rating": 5.0, "coordinates": {"latitude": 40.7077789, "longitude": -73.9429626}, "transactions": [], "location": {"address1": "176 Graham Ave", "address2": "Ste 1R", "address3": "", "city": "Brooklyn", "zip_code": "11206", "country": "US", "state": "NY", "display_address": ["176 Graham Ave", "Ste 1R", "Brooklyn, NY 11206"]}, "phone": "+16463636357", "display_phone": "(646) 363-6357", "distance": 3048.641740092682}, {"id": "1S1F4umlWY1RsgB0lpgWqA", "alias": "the-signature-society-mount-vernon", "name": "The Signature Society", "image_url": "https://s3-media3.fl.yelpcdn.com/bphoto/twYOB2FglFFIGMq9UPqn5w/o.jpg", "is_closed": false, "url": "https://www.yelp.com/biz/the-signature-society-mount-vernon?adjust_creative=OD45_sigUUSBobJ_eVs01w&utm_campaign=yelp_api_v3&utm_medium=api_v3_business_search&utm_source=OD45_sigUUSBobJ_eVs01w", "review_count": 1, "categories": [{"alias": "festivals", "title": "Festivals"}], "rating": 5.0, "coordinates": {"latitude": 40.908516636814994, "longitude": -73.8217087200471}, "transactions": [], "location": {"address1": "", "address2": "", "address3": null, "city": "Mount Vernon", "zip_code": "10553", "country": "US", "state": "NY", "display_address": ["Mount Vernon, NY 10553"]}, "phone": "+19143639241", "display_phone": "(914) 363-9241", "distance": 26036.130357789643}, {"id": "AF3bRZRXUIKLEKuxVGpTCw", "alias": "filmonefest-atlantic-highlands", "name": "FilmOneFest", "image_url": "https://s3-media2.fl.yelpcdn.com/bphoto/U9lj9OCK3Q31Cg9D9aqXtQ/o.jpg", "is_closed": false, "url": "https://www.yelp.com/biz/filmonefest-atlantic-highlands?adjust_creative=OD45_sigUUSBobJ_eVs01w&utm_campaign=yelp_api_v3&utm_medium=api_v3_business_search&utm_source=OD45_sigUUSBobJ_eVs01w", "review_count": 1, "categories": [{"alias": "festivals", "title": "Festivals"}], "rating": 4.0, "coordinates": {"latitude": 40.4170895731713, "longitude": -74.0362878089535}, "transactions": [], "location": {"address1": "1 Simon Lake Dr", "address2": "", "address3": null, "city": "Atlantic Highlands", "zip_code": "07716", "country": "US", "state": "NJ", "display_address": ["1 Simon Lake Dr", "Atlantic Highlands, NJ 07716"]}, "phone": "+17327377160", "display_phone": "(732) 737-7160", "distance": 32592.960889036716}, {"id": "ndl4yEKIt6UqSocj5BZN5w", "alias": "state-fair-meadowlands-east-rutherford", "name": "State Fair Meadowlands", "image_url": "https://s3-media2.fl.yelpcdn.com/bphoto/OzS_wWFuBbC18jCfq52W0Q/o.jpg", "is_closed": false, "url": "https://www.yelp.com/biz/state-fair-meadowlands-east-rutherford?adjust_creative=OD45_sigUUSBobJ_eVs01w&utm_campaign=yelp_api_v3&utm_medium=api_v3_business_search&utm_source=OD45_sigUUSBobJ_eVs01w", "review_count": 87, "categories": [{"alias": "festivals", "title": "Festivals"}], "rating": 2.5, "coordinates": {"latitude": 40.8118062269197, "longitude": -74.0673057525008}, "transactions": [], "location": {"address1": "102 Rte 120", "address2": "", "address3": "", "city": "East Rutherford", "zip_code": "07073", "country": "US", "state": "NJ", "display_address": ["102 Rte 120", "East Rutherford, NJ 07073"]}, "phone": "+12015038083", "display_phone": "(201) 503-8083", "distance": 13818.644149683265}, {"id": "5U5SKd5K6j__rsXHHh9STw", "alias": "magic-of-lights-new-jersey-holmdel", "name": "Magic of Lights - New Jersey", "image_url": "https://s3-media1.fl.yelpcdn.com/bphoto/iyY8U2LE3uFbqjAkkwd18w/o.jpg", "is_closed": false, "url": "https://www.yelp.com/biz/magic-of-lights-new-jersey-holmdel?adjust_creative=OD45_sigUUSBobJ_eVs01w&utm_campaign=yelp_api_v3&utm_medium=api_v3_business_search&utm_source=OD45_sigUUSBobJ_eVs01w", "review_count": 110, "categories": [{"alias": "festivals", "title": "Festivals"}], "rating": 1.5, "coordinates": {"latitude": 40.3944372, "longitude": -74.1761428}, "transactions": [], "location": {"address1": "116 Garden State Pkwy", "address2": null, "address3": "", "city": "Holmdel", "zip_code": "07733", "country": "US", "state": "NJ", "display_address": ["116 Garden State Pkwy", "Holmdel, NJ 07733"]}, "phone": "", "display_phone": "", "distance": 38594.901199555105}]}